vidaug/__init__.py
vidaug/classification/__init__.py
vidaug/classification/augment.py
vidaug/classification/utils/__init__.py
vidaug/classification/utils/filter.py
vidaug/classification/utils/util.py
VideoAug-1.0.0.dist-info/LICENSE
VideoAug-1.0.0.dist-info/METADATA
VideoAug-1.0.0.dist-info/WHEEL
VideoAug-1.0.0.dist-info/top_level.txt
VideoAug-1.0.0.dist-info/RECORD
