Metadata-Version: 2.1
Name: VideoAug
Version: 1.0.0
Summary: Toolbox for Video Augmentation
Home-page: https://github.com/seyedamanzargari/VidAug
Author: SeyedAman Zargari
Author-email: seyedamanzargari@gmail.com
License: MIT
Platform: UNKNOWN
License-File: LICENSE
Requires-Dist: albumentations
Requires-Dist: opencv-python
Requires-Dist: tqdm
